Metadata-Version: 2.1
Name: oneNeuron-pypi-jhv
Version: 0.0.2
Summary: This is an implementation of Perceptron
Home-page: https://github.com/jhv/oneNeuron_pypi
Author: jhv
Author-email: author@example.com
License: UNKNOWN
Project-URL: Bug Tracker, https://github.com/{USER_NAME}/{PROJECT_NAME}/issues
Platform: UNKNOWN
Classifier: Programming Language :: Python :: 3
Classifier: License :: OSI Approved :: MIT License
Classifier: Operating System :: OS Independent
Requires-Python: >=3.7
License-File: LICENSE
Requires-Dist: numpy
Requires-Dist: tqdm
